KahootConnect/__init__.py
KahootConnect-0.2.6.dist-info/LICENSE
KahootConnect-0.2.6.dist-info/METADATA
KahootConnect-0.2.6.dist-info/WHEEL
KahootConnect-0.2.6.dist-info/top_level.txt
KahootConnect-0.2.6.dist-info/RECORD
